{
  "db_name": "PostgreSQL",
  "query": "\n                INSERT INTO user_email_confirmation_codes\n                  (user_email_confirmation_code_id, user_email_id, code, created_at, expires_at)\n                VALUES ($1, $2, $3, $4, $5)\n            ",
  "describe": {
    "columns": [],
    "parameters": {
      "Left": [
        "Uuid",
        "Uuid",
        "Text",
        "Timestamptz",
        "Timestamptz"
      ]
    },
    "nullable": []
  },
  "hash": "b515bbfb331e46acd3c0219f09223cc5d8d31cb41287e693dcb82c6e199f7991"
}
