{
  "db_name": "PostgreSQL",
  "query": "\n                INSERT INTO upstream_oauth_authorization_sessions (\n                    upstream_oauth_authorization_session_id,\n                    upstream_oauth_provider_id,\n                    state,\n                    code_challenge_verifier,\n                    nonce,\n                    created_at,\n                    completed_at,\n                    consumed_at,\n                    id_token\n                ) VALUES ($1, $2, $3, $4, $5, $6, NULL, NULL, NULL)\n            ",
  "describe": {
    "columns": [],
    "parameters": {
      "Left": [
        "Uuid",
        "Uuid",
        "Text",
        "Text",
        "Text",
        "Timestamptz"
      ]
    },
    "nullable": []
  },
  "hash": "64e6ea47c2e877c1ebe4338d64d9ad8a6c1c777d1daea024b8ca2e7f0dd75b0f"
}
